[
	{
		"Id" : 1,
		"Start time" : "4/9/2026 8:21",
		"Completion time" : "4/9/2026 8:23",
		"Email" : "jlopez7@my.yearupunited.org",
		"Name" : "jonathan lopez",
		"How often do you visit Tribe" : "First time",
		"Did you attend Tribe by yourself or with someone else?" : "With another person",
		"How did you hear about this event?" : "Social media;",
		"How satisfied are you with the following .Wi-Fi Quality" : "Satisfactory",
		"How satisfied are you with the following .portion size" : "Very Satisfied",
		"How satisfied are you with the following .Cost of food" : "Very Satisfied",
		"How satisfied are you with the following .Cost of drinks" : "Very Satisfied",
		"How satisfied are you with the following .Quality of food" : "Very Satisfied",
		"How satisfied are you with the following .Variety of food" : "Satisfactory",
		"How satisfied are you with the following .Music" : "Very Satisfied",
		"How satisfied are you with the following .Security" : "Satisfactory",
		"How satisfied are you with the following .Restroom facilities" : "Satisfactory",
		"How satisfied are you with the following .Parking" : "Okay",
		"Would you be interested in a rewards/ loyalty program?" : "Yes",
		"What kind of rewards do you prefer?" : "Student discount;Earn 1 point for every $1 you spend ;",
		"Recommendation" : "Very likely",
		"What changes would you like Tribe to improve in (if any)?" : "Maybe someday invest in a parking lot so it's not difficult to find parking to go inside."
	},
	{
		"Id" : 2,
		"Start time" : "4/9/2026 8:40",
		"Completion time" : "4/9/2026 8:43",
		"Email" : "dkabakibi@my.yearupunited.org",
		"Name" : "dania kabakibi",
		"How often do you visit Tribe" : "Once a Week",
		"Did you attend Tribe by yourself or with someone else?" : "With more than one person",
		"How did you hear about this event?" : "Social media;",
		"How satisfied are you with the following .Wi-Fi Quality" : "Very Satisfied",
		"How satisfied are you with the following .portion size" : "Satisfactory",
		"How satisfied are you with the following .Cost of food" : "Satisfactory",
		"How satisfied are you with the following .Cost of drinks" : "Satisfactory",
		"How satisfied are you with the following .Quality of food" : "Very Satisfied",
		"How satisfied are you with the following .Variety of food" : "Very Satisfied",
		"How satisfied are you with the following .Music" : "Very Satisfied",
		"How satisfied are you with the following .Security" : "Very Satisfied",
		"How satisfied are you with the following .Restroom facilities" : "Satisfactory",
		"How satisfied are you with the following .Parking" : "Very Satisfied",
		"Would you be interested in a rewards/ loyalty program?" : "Yes",
		"What kind of rewards do you prefer?" : "Free Dessert with any drink after 4 visits;Earn 1 point for every $1 you spend ;",
		"Recommendation" : "Very likely",
		"What changes would you like Tribe to improve in (if any)?" : ""
	},
	{
		"Id" : 3,
		"Start time" : "4/9/2026 8:56",
		"Completion time" : "4/9/2026 8:56",
		"Email" : "mblack@my.yearupunited.org",
		"Name" : "maia black",
		"How often do you visit Tribe" : "First time",
		"Did you attend Tribe by yourself or with someone else?" : "With another person",
		"How did you hear about this event?" : "Social media;",
		"How satisfied are you with the following .Wi-Fi Quality" : "Very Satisfied",
		"How satisfied are you with the following .portion size" : "Very Satisfied",
		"How satisfied are you with the following .Cost of food" : "Very Satisfied",
		"How satisfied are you with the following .Cost of drinks" : "Very Satisfied",
		"How satisfied are you with the following .Quality of food" : "Very Satisfied",
		"How satisfied are you with the following .Variety of food" : "Very Satisfied",
		"How satisfied are you with the following .Music" : "Satisfactory",
		"How satisfied are you with the following .Security" : "Very Satisfied",
		"How satisfied are you with the following .Restroom facilities" : "Very Satisfied",
		"How satisfied are you with the following .Parking" : "Okay",
		"Would you be interested in a rewards/ loyalty program?" : "Yes",
		"What kind of rewards do you prefer?" : "Earn 1 point for every $1 you spend ;",
		"Recommendation" : "Very likely",
		"What changes would you like Tribe to improve in (if any)?" : ""
	},
	{
		"Id" : 4,
		"Start time" : "4/9/2026 8:39",
		"Completion time" : "4/9/2026 9:21",
		"Email" : "pgreen-holloway@my.yearupunited.org",
		"Name" : "patrick green-holloway",
		"How often do you visit Tribe" : "First time",
		"Did you attend Tribe by yourself or with someone else?" : "With another person",
		"How did you hear about this event?" : "Word-of-mouth;Social media;Flyer;",
		"How satisfied are you with the following .Wi-Fi Quality" : "Very Satisfied",
		"How satisfied are you with the following .portion size" : "Very Satisfied",
		"How satisfied are you with the following .Cost of food" : "Very Satisfied",
		"How satisfied are you with the following .Cost of drinks" : "Very Satisfied",
		"How satisfied are you with the following .Quality of food" : "Very Satisfied",
		"How satisfied are you with the following .Variety of food" : "Very Satisfied",
		"How satisfied are you with the following .Music" : "Very Satisfied",
		"How satisfied are you with the following .Security" : "Very Satisfied",
		"How satisfied are you with the following .Restroom facilities" : "Very Satisfied",
		"How satisfied are you with the following .Parking" : "Very Satisfied",
		"Would you be interested in a rewards/ loyalty program?" : "Yes",
		"What kind of rewards do you prefer?" : "Student discount;Free Dessert with any drink after 4 visits;Combo Reward ( coffee + dessert bundle);Earn 1 point for every $1 you spend ;VIP Art Night ;Members only tasting event ;",
		"Recommendation" : "Very likely",
		"What changes would you like Tribe to improve in (if any)?" : ""
	},
	{
		"Id" : 5,
		"Start time" : "4/9/2026 21:49",
		"Completion time" : "4/9/2026 21:50",
		"Email" : "ktyler@my.yearupunited.org",
		"Name" : "kendra tyler",
		"How often do you visit Tribe" : "First time",
		"Did you attend Tribe by yourself or with someone else?" : "With another person",
		"How did you hear about this event?" : "Word-of-mouth;",
		"How satisfied are you with the following .Wi-Fi Quality" : "Very Satisfied",
		"How satisfied are you with the following .portion size" : "Satisfactory",
		"How satisfied are you with the following .Cost of food" : "Satisfactory",
		"How satisfied are you with the following .Cost of drinks" : "Very Satisfied",
		"How satisfied are you with the following .Quality of food" : "Very Satisfied",
		"How satisfied are you with the following .Variety of food" : "Very Satisfied",
		"How satisfied are you with the following .Music" : "Very Satisfied",
		"How satisfied are you with the following .Security" : "Satisfactory",
		"How satisfied are you with the following .Restroom facilities" : "Very Satisfied",
		"How satisfied are you with the following .Parking" : "Okay",
		"Would you be interested in a rewards/ loyalty program?" : "Yes",
		"What kind of rewards do you prefer?" : "Free Dessert with any drink after 4 visits;Combo Reward ( coffee + dessert bundle);Earn 1 point for every $1 you spend ;VIP Art Night ;Members only tasting event ;Student discount;",
		"Recommendation" : "Very likely",
		"What changes would you like Tribe to improve in (if any)?" : "Shorter wait time "
	},
	{
		"Id" : 6,
		"Start time" : "4/9/2026 23:50",
		"Completion time" : "4/9/2026 23:52",
		"Email" : "mtariq@my.yearupunited.org",
		"Name" : "malaika tariq",
		"How often do you visit Tribe" : "Once a Month",
		"Did you attend Tribe by yourself or with someone else?" : "With more than one person",
		"How did you hear about this event?" : "Social media;",
		"How satisfied are you with the following .Wi-Fi Quality" : "Very Satisfied",
		"How satisfied are you with the following .portion size" : "Very Satisfied",
		"How satisfied are you with the following .Cost of food" : "Very Satisfied",
		"How satisfied are you with the following .Cost of drinks" : "Very Satisfied",
		"How satisfied are you with the following .Quality of food" : "Very Satisfied",
		"How satisfied are you with the following .Variety of food" : "Satisfactory",
		"How satisfied are you with the following .Music" : "Satisfactory",
		"How satisfied are you with the following .Security" : "Very Satisfied",
		"How satisfied are you with the following .Restroom facilities" : "Very Satisfied",
		"How satisfied are you with the following .Parking" : "Satisfactory",
		"Would you be interested in a rewards/ loyalty program?" : "Yes",
		"What kind of rewards do you prefer?" : "Student discount;Combo Reward ( coffee + dessert bundle);",
		"Recommendation" : "Very likely",
		"What changes would you like Tribe to improve in (if any)?" : ""
	},
	{
		"Id" : 7,
		"Start time" : "4/10/2026 17:55",
		"Completion time" : "4/10/2026 17:56",
		"Email" : "sweaver@my.yearupunited.org",
		"Name" : "sharya weaver",
		"How often do you visit Tribe" : "First time",
		"Did you attend Tribe by yourself or with someone else?" : "With another person",
		"How did you hear about this event?" : "Word-of-mouth;",
		"How satisfied are you with the following .Wi-Fi Quality" : "Okay",
		"How satisfied are you with the following .portion size" : "Satisfactory",
		"How satisfied are you with the following .Cost of food" : "Okay",
		"How satisfied are you with the following .Cost of drinks" : "Okay",
		"How satisfied are you with the following .Quality of food" : "Very Satisfied",
		"How satisfied are you with the following .Variety of food" : "Very Satisfied",
		"How satisfied are you with the following .Music" : "Satisfactory",
		"How satisfied are you with the following .Security" : "Okay",
		"How satisfied are you with the following .Restroom facilities" : "Okay",
		"How satisfied are you with the following .Parking" : "Dissatisfied",
		"Would you be interested in a rewards/ loyalty program?" : "Yes",
		"What kind of rewards do you prefer?" : "Earn 1 point for every $1 you spend ;",
		"Recommendation" : "Likely",
		"What changes would you like Tribe to improve in (if any)?" : ""
	}
]
